README.rst
setup.py
MedianHeapPython/__init__.py
MedianHeapPython/medianFinder.py
MedianHeapPython.egg-info/PKG-INFO
MedianHeapPython.egg-info/SOURCES.txt
MedianHeapPython.egg-info/dependency_links.txt
MedianHeapPython.egg-info/top_level.txt