Metadata-Version: 1.0
Name: MedianHeapPython
Version: 1.0.6
Summary: Calculates the median of a data stream in O(log n) time using a heap!
Home-page: https://github.com/csbuja/MedianHeapPython
Author: Spencer Buja
Author-email: csbuja@umich.edu
License: MIT
Platform: ALL
